{
    "sums": [
        {
            "username": "airrack",
            "displayName": "airrack",
            "totalFollowers": 20197100
        },
        {
            "username": "aztrosist",
            "displayName": "aztrosist",
            "totalFollowers": 1409250
        },
        {
            "username": "blorg",
            "displayName": "Blorg",
            "totalFollowers": 276591
        },
        {
            "username": "caseyneistat",
            "displayName": "Casey Neistat",
            "totalFollowers": 19924200
        },
        {
            "username": "coldones",
            "displayName": "Cold Ones",
            "totalFollowers": 5353400
        },
        {
            "username": "corridor",
            "displayName": "Corridor",
            "totalFollowers": 18053400
        },
        {
            "username": "critikal",
            "displayName": "Critikal",
            "totalFollowers": 26586900
        },
        {
            "username": "cyranek",
            "displayName": "Cyranek",
            "totalFollowers": 1552815
        },
        {
            "username": "dailydose",
            "displayName": "Daily Dose Of Internet",
            "totalFollowers": 21027200
        },
        {
            "username": "dolandark",
            "displayName": "Dolan Dark",
            "totalFollowers": 5601688
        },
        {
            "username": "dunkey",
            "displayName": "dunkey",
            "totalFollowers": 10337100
        },
        {
            "username": "glorb",
            "displayName": "Glorb",
            "totalFollowers": 2377750
        },
        {
            "username": "grandayy",
            "displayName": "Grandayy",
            "totalFollowers": 7643321
        },
        {
            "username": "gus",
            "displayName": "Gus Johnson",
            "totalFollowers": 4528700
        },
        {
            "username": "ishowspeed",
            "displayName": "iShowSpeed",
            "totalFollowers": 97249000
        },
        {
            "username": "jejkobbb",
            "displayName": "Jejkobbb",
            "totalFollowers": 345770
        },
        {
            "username": "jschlatt",
            "displayName": "jschlatt",
            "totalFollowers": 24910875
        },
        {
            "username": "kadz",
            "displayName": "kadz",
            "totalFollowers": 2402620
        },
        {
            "username": "kostamoinen",
            "displayName": "Kostamoinen",
            "totalFollowers": 4001300
        },
        {
            "username": "lazar",
            "displayName": "Lazar Beam",
            "totalFollowers": 32947000
        },
        {
            "username": "linustech",
            "displayName": "Linus Tech Tips",
            "totalFollowers": 35693098
        },
        {
            "username": "ludwig",
            "displayName": "ludwig",
            "totalFollowers": 18118000
        },
        {
            "username": "markrober",
            "displayName": "Mark Rober",
            "totalFollowers": 69600000
        },
        {
            "username": "mkbhd",
            "displayName": "Marques Brownlee",
            "totalFollowers": 36078000
        },
        {
            "username": "maxxjamez",
            "displayName": "Maxx Jamez",
            "totalFollowers": 103529
        },
        {
            "username": "mega64",
            "displayName": "Mega64",
            "totalFollowers": 924800
        },
        {
            "username": "mikopath",
            "displayName": "Mikopath",
            "totalFollowers": 63943
        },
        {
            "username": "mintblitz",
            "displayName": "Mint Blitz",
            "totalFollowers": 450900
        },
        {
            "username": "mrbeast",
            "displayName": "Mr. Beast",
            "totalFollowers": 712234354
        },
        {
            "username": "ninja",
            "displayName": "Ninja",
            "totalFollowers": 74118000
        },
        {
            "username": "oboeshoesgames",
            "displayName": "oboeshoesgames",
            "totalFollowers": 427065
        },
        {
            "username": "octopox",
            "displayName": "Octopox",
            "totalFollowers": 2940
        },
        {
            "username": "pewdiepie",
            "displayName": "PewDiePie",
            "totalFollowers": 131945999
        },
        {
            "username": "pinkieoats",
            "displayName": "Pinkie Oats",
            "totalFollowers": 28955
        },
        {
            "username": "rabbert",
            "displayName": "Rabbert",
            "totalFollowers": 21192000
        },
        {
            "username": "ryitus",
            "displayName": "Ryitus",
            "totalFollowers": 17390
        },
        {
            "username": "scottthewoz",
            "displayName": "ScottTheWoz",
            "totalFollowers": 3194300
        },
        {
            "username": "smosh",
            "displayName": "Smosh",
            "totalFollowers": 67355500
        },
        {
            "username": "sven",
            "displayName": "Sven Johnson",
            "totalFollowers": 1230999
        },
        {
            "username": "test",
            "displayName": "Testing",
            "totalFollowers": 458049647
        },
        {
            "username": "gametheory",
            "displayName": "The Game Theorists",
            "totalFollowers": 45541800
        },
        {
            "username": "gamingcave",
            "displayName": "The Gaming Cave",
            "totalFollowers": 248
        },
        {
            "username": "thrilldawill",
            "displayName": "ThrillDaWill",
            "totalFollowers": 136253
        },
        {
            "username": "trevorwallace",
            "displayName": "Trevor Wallace",
            "totalFollowers": 23391791
        },
        {
            "username": "vsauce",
            "displayName": "VSauce",
            "totalFollowers": 31030000
        },
        {
            "username": "zimonitrome",
            "displayName": "ZimoNitrome",
            "totalFollowers": 355597
        }
    ],
    "timeRetrieved": 1730466871908
}