{
    "sums": [
        {
            "username": "airrack",
            "displayName": "airrack",
            "totalFollowers": 22545200
        },
        {
            "username": "aztrosist",
            "displayName": "aztrosist",
            "totalFollowers": 1390555
        },
        {
            "username": "blorg",
            "displayName": "Blorg",
            "totalFollowers": 843865
        },
        {
            "username": "caseyneistat",
            "displayName": "Casey Neistat",
            "totalFollowers": 19619700
        },
        {
            "username": "coldones",
            "displayName": "Cold Ones",
            "totalFollowers": 5725600
        },
        {
            "username": "corridor",
            "displayName": "Corridor",
            "totalFollowers": 18565800
        },
        {
            "username": "critikal",
            "displayName": "Critikal",
            "totalFollowers": 29093745
        },
        {
            "username": "cyranek",
            "displayName": "Cyranek",
            "totalFollowers": 1525089
        },
        {
            "username": "dailydose",
            "displayName": "Daily Dose Of Internet",
            "totalFollowers": 22049400
        },
        {
            "username": "dolandark",
            "displayName": "Dolan Dark",
            "totalFollowers": 5689319
        },
        {
            "username": "dunkey",
            "displayName": "dunkey",
            "totalFollowers": 9422600
        },
        {
            "username": "glorb",
            "displayName": "Glorb",
            "totalFollowers": 2980897
        },
        {
            "username": "grandayy",
            "displayName": "Grandayy",
            "totalFollowers": 7612048
        },
        {
            "username": "gus",
            "displayName": "Gus Johnson",
            "totalFollowers": 4377836
        },
        {
            "username": "ishowspeed",
            "displayName": "iShowSpeed",
            "totalFollowers": 137700000
        },
        {
            "username": "jejkobbb",
            "displayName": "Jejkobbb",
            "totalFollowers": 356470
        },
        {
            "username": "jschlatt",
            "displayName": "jschlatt",
            "totalFollowers": 26772107
        },
        {
            "username": "kadz",
            "displayName": "kadz",
            "totalFollowers": 4243330
        },
        {
            "username": "kostamoinen",
            "displayName": "Kostamoinen",
            "totalFollowers": 4928100
        },
        {
            "username": "lazar",
            "displayName": "Lazar Beam",
            "totalFollowers": 34216000
        },
        {
            "username": "linustech",
            "displayName": "Linus Tech Tips",
            "totalFollowers": 36169106
        },
        {
            "username": "ludwig",
            "displayName": "ludwig",
            "totalFollowers": 15772000
        },
        {
            "username": "markrober",
            "displayName": "Mark Rober",
            "totalFollowers": 84600000
        },
        {
            "username": "mkbhd",
            "displayName": "Marques Brownlee",
            "totalFollowers": 37838000
        },
        {
            "username": "maxxjamez",
            "displayName": "Maxx Jamez",
            "totalFollowers": 102975
        },
        {
            "username": "mega64",
            "displayName": "Mega64",
            "totalFollowers": 882900
        },
        {
            "username": "mikopath",
            "displayName": "Mikopath",
            "totalFollowers": 65598
        },
        {
            "username": "mintblitz",
            "displayName": "Mint Blitz",
            "totalFollowers": 557500
        },
        {
            "username": "mrbeast",
            "displayName": "Mr. Beast",
            "totalFollowers": 879334726
        },
        {
            "username": "ninja",
            "displayName": "Ninja",
            "totalFollowers": 74403700
        },
        {
            "username": "oboeshoesgames",
            "displayName": "oboeshoesgames",
            "totalFollowers": 401583
        },
        {
            "username": "octopox",
            "displayName": "Octopox",
            "totalFollowers": 2845
        },
        {
            "username": "pewdiepie",
            "displayName": "PewDiePie",
            "totalFollowers": 131689669
        },
        {
            "username": "pinkieoats",
            "displayName": "Pinkie Oats",
            "totalFollowers": 28505
        },
        {
            "username": "rabbert",
            "displayName": "Rabbert",
            "totalFollowers": 22510500
        },
        {
            "username": "ryitus",
            "displayName": "Ryitus",
            "totalFollowers": 12688
        },
        {
            "username": "scottthewoz",
            "displayName": "ScottTheWoz",
            "totalFollowers": 3393700
        },
        {
            "username": "smosh",
            "displayName": "Smosh",
            "totalFollowers": 69279429
        },
        {
            "username": "sven",
            "displayName": "Sven Johnson",
            "totalFollowers": 1533139
        },
        {
            "username": "test",
            "displayName": "Testing",
            "totalFollowers": 569518534
        },
        {
            "username": "gametheory",
            "displayName": "The Game Theorists",
            "totalFollowers": 45999300
        },
        {
            "username": "gamingcave",
            "displayName": "The Gaming Cave",
            "totalFollowers": 529
        },
        {
            "username": "thrilldawill",
            "displayName": "ThrillDaWill",
            "totalFollowers": 138903
        },
        {
            "username": "trevorwallace",
            "displayName": "Trevor Wallace",
            "totalFollowers": 27571028
        },
        {
            "username": "vsauce",
            "displayName": "VSauce",
            "totalFollowers": 33142200
        },
        {
            "username": "zimonitrome",
            "displayName": "ZimoNitrome",
            "totalFollowers": 362106
        }
    ],
    "timeRetrieved": 1765549067625
}