{
    "histories": [
        {
            "platformName": "YouTube",
            "username": "summit1g",
            "countUnits": 0,
            "historicalCounts": [
                {
                    "count": 807000,
                    "timestamp": 1767029740089
                }
            ]
        },
        {
            "platformName": "Instagram",
            "username": "summit1g",
            "countUnits": 0,
            "historicalCounts": []
        },
        {
            "platformName": "Tik Tok",
            "username": "summit1g",
            "countUnits": 0,
            "historicalCounts": [
                {
                    "count": 2,
                    "timestamp": 1767029777042
                }
            ]
        },
        {
            "platformName": "Twitch",
            "username": "summit1g",
            "countUnits": 0,
            "historicalCounts": [
                {
                    "count": 6400000,
                    "timestamp": 1767029769667
                },
                {
                    "count": 0,
                    "timestamp": 1767218800092
                }
            ]
        },
        {
            "platformName": "Twitter",
            "username": "summit1g",
            "countUnits": 0,
            "historicalCounts": [
                {
                    "count": 976500,
                    "timestamp": 1767029761731
                },
                {
                    "count": 976400,
                    "timestamp": 1767218792437
                }
            ]
        },
        {
            "platformName": "YouTube",
            "username": "summit1g",
            "countUnits": 1,
            "historicalCounts": [
                {
                    "count": 201116916,
                    "timestamp": 1767029740089
                },
                {
                    "count": 201212906,
                    "timestamp": 1767107849519
                },
                {
                    "count": 201220959,
                    "timestamp": 1767187992527
                },
                {
                    "count": 201264579,
                    "timestamp": 1767218771503
                }
            ]
        }
    ]
}