{
    "histories": [
        {
            "platformName": "YouTube",
            "username": "TrevorWallace",
            "countUnits": 0,
            "historicalCounts": [
                {
                    "count": 5940000,
                    "timestamp": 1757472612196
                },
                {
                    "count": 5950000,
                    "timestamp": 1758490183103
                },
                {
                    "count": 5960000,
                    "timestamp": 1759119462190
                },
                {
                    "count": 5970000,
                    "timestamp": 1760101493546
                },
                {
                    "count": 5980000,
                    "timestamp": 1760445312512
                },
                {
                    "count": 5990000,
                    "timestamp": 1761522897353
                },
                {
                    "count": 6000000,
                    "timestamp": 1762321919920
                }
            ]
        },
        {
            "platformName": "YouTube",
            "username": "wrevortallace5917",
            "countUnits": 0,
            "historicalCounts": [
                {
                    "count": 29800,
                    "timestamp": 1757472617942
                },
                {
                    "count": 29900,
                    "timestamp": 1760101499812
                }
            ]
        },
        {
            "platformName": "YouTube",
            "username": "StiffSocks",
            "countUnits": 0,
            "historicalCounts": [
                {
                    "count": 376000,
                    "timestamp": 1757472623894
                },
                {
                    "count": 377000,
                    "timestamp": 1758208235366
                },
                {
                    "count": 378000,
                    "timestamp": 1758490193843
                },
                {
                    "count": 379000,
                    "timestamp": 1758667639205
                },
                {
                    "count": 384000,
                    "timestamp": 1759119472746
                },
                {
                    "count": 386000,
                    "timestamp": 1760101506017
                },
                {
                    "count": 387000,
                    "timestamp": 1760445323461
                },
                {
                    "count": 388000,
                    "timestamp": 1760808887857
                },
                {
                    "count": 391000,
                    "timestamp": 1761050957069
                },
                {
                    "count": 394000,
                    "timestamp": 1761256679563
                },
                {
                    "count": 398000,
                    "timestamp": 1761522907796
                },
                {
                    "count": 408000,
                    "timestamp": 1762208008116
                },
                {
                    "count": 412000,
                    "timestamp": 1762321931708
                }
            ]
        },
        {
            "platformName": "Instagram",
            "username": "trevorwallace",
            "countUnits": 0,
            "historicalCounts": [
                {
                    "count": 5000000,
                    "timestamp": 1756586585926
                }
            ]
        },
        {
            "platformName": "Tik Tok",
            "username": "trevorwallace",
            "countUnits": 0,
            "historicalCounts": [
                {
                    "count": 11300000,
                    "timestamp": 1757472653878
                },
                {
                    "count": 11400000,
                    "timestamp": 1758490222550
                }
            ]
        },
        {
            "platformName": "Twitter",
            "username": "TrevWall",
            "countUnits": 0,
            "historicalCounts": [
                {
                    "count": 1674,
                    "timestamp": 1738848803741
                },
                {
                    "count": 39,
                    "timestamp": 1762208023306
                },
                {
                    "count": 35,
                    "timestamp": 1762321952910
                }
            ]
        },
        {
            "platformName": "Facebook",
            "username": "TrevorWallaceComedy",
            "countUnits": 0,
            "historicalCounts": [
                {
                    "count": 4099999.9999999995,
                    "timestamp": 1757472661268
                },
                {
                    "count": 4200000,
                    "timestamp": 1760533508412
                }
            ]
        },
        {
            "platformName": "YouTube",
            "username": "TrevorWallace",
            "countUnits": 1,
            "historicalCounts": [
                {
                    "count": 3280447129,
                    "timestamp": 1757472612196
                },
                {
                    "count": 3280538934,
                    "timestamp": 1757509485528
                },
                {
                    "count": 3280962845,
                    "timestamp": 1757520023127
                },
                {
                    "count": 3281279908,
                    "timestamp": 1757595046799
                },
                {
                    "count": 3282123810,
                    "timestamp": 1757680328138
                },
                {
                    "count": 3283429517,
                    "timestamp": 1757780866015
                },
                {
                    "count": 3283919998,
                    "timestamp": 1757866145542
                },
                {
                    "count": 3291330703,
                    "timestamp": 1758208224116
                },
                {
                    "count": 3297663930,
                    "timestamp": 1758490183103
                },
                {
                    "count": 3300913944,
                    "timestamp": 1758667627689
                },
                {
                    "count": 3301819831,
                    "timestamp": 1758718832831
                },
                {
                    "count": 3310185834,
                    "timestamp": 1759119462190
                },
                {
                    "count": 3312757225,
                    "timestamp": 1759237312387
                },
                {
                    "count": 3314252109,
                    "timestamp": 1759323935834
                },
                {
                    "count": 3329549813,
                    "timestamp": 1760101493546
                },
                {
                    "count": 3329985256,
                    "timestamp": 1760136575945
                },
                {
                    "count": 3332486872,
                    "timestamp": 1760313426832
                },
                {
                    "count": 3335245094,
                    "timestamp": 1760445312512
                },
                {
                    "count": 3336314879,
                    "timestamp": 1760533462409
                },
                {
                    "count": 3340767346,
                    "timestamp": 1760808877372
                },
                {
                    "count": 3345908429,
                    "timestamp": 1761050946079
                },
                {
                    "count": 3351498201,
                    "timestamp": 1761256668836
                },
                {
                    "count": 3359327860,
                    "timestamp": 1761522897353
                },
                {
                    "count": 3383522955,
                    "timestamp": 1762207996118
                },
                {
                    "count": 3387020761,
                    "timestamp": 1762321919920
                }
            ]
        },
        {
            "platformName": "YouTube",
            "username": "wrevortallace5917",
            "countUnits": 1,
            "historicalCounts": [
                {
                    "count": 3460390,
                    "timestamp": 1757472617942
                },
                {
                    "count": 3460492,
                    "timestamp": 1757475303872
                },
                {
                    "count": 3460641,
                    "timestamp": 1757520028695
                },
                {
                    "count": 3460669,
                    "timestamp": 1757595052949
                },
                {
                    "count": 3460727,
                    "timestamp": 1757680334011
                },
                {
                    "count": 3460970,
                    "timestamp": 1757780871675
                },
                {
                    "count": 3461092,
                    "timestamp": 1757866150836
                },
                {
                    "count": 3461485,
                    "timestamp": 1758208229741
                },
                {
                    "count": 3462063,
                    "timestamp": 1758490188557
                },
                {
                    "count": 3462360,
                    "timestamp": 1758667633392
                },
                {
                    "count": 3462403,
                    "timestamp": 1758718838405
                },
                {
                    "count": 3463326,
                    "timestamp": 1759119467528
                },
                {
                    "count": 3463615,
                    "timestamp": 1759237318183
                },
                {
                    "count": 3463737,
                    "timestamp": 1759323941202
                },
                {
                    "count": 3465299,
                    "timestamp": 1760101499812
                },
                {
                    "count": 3465431,
                    "timestamp": 1760136581321
                },
                {
                    "count": 3465760,
                    "timestamp": 1760313432488
                },
                {
                    "count": 3466018,
                    "timestamp": 1760445317641
                },
                {
                    "count": 3466088,
                    "timestamp": 1760533468274
                },
                {
                    "count": 3466926,
                    "timestamp": 1760808882481
                },
                {
                    "count": 3467184,
                    "timestamp": 1761050951629
                },
                {
                    "count": 3467680,
                    "timestamp": 1761256674484
                },
                {
                    "count": 3468243,
                    "timestamp": 1761522902524
                },
                {
                    "count": 3469444,
                    "timestamp": 1762208002919
                },
                {
                    "count": 3469622,
                    "timestamp": 1762321925697
                }
            ]
        },
        {
            "platformName": "YouTube",
            "username": "StiffSocks",
            "countUnits": 1,
            "historicalCounts": [
                {
                    "count": 157741347,
                    "timestamp": 1757472623894
                },
                {
                    "count": 157796910,
                    "timestamp": 1757509496788
                },
                {
                    "count": 157918009,
                    "timestamp": 1757520033846
                },
                {
                    "count": 158023002,
                    "timestamp": 1757595058280
                },
                {
                    "count": 158310968,
                    "timestamp": 1757680339195
                },
                {
                    "count": 158718038,
                    "timestamp": 1757780877039
                },
                {
                    "count": 158894585,
                    "timestamp": 1757866156022
                },
                {
                    "count": 160129439,
                    "timestamp": 1758208235366
                },
                {
                    "count": 161068606,
                    "timestamp": 1758490193843
                },
                {
                    "count": 162055274,
                    "timestamp": 1758667639205
                },
                {
                    "count": 162731174,
                    "timestamp": 1758718843781
                },
                {
                    "count": 169202222,
                    "timestamp": 1759119472746
                },
                {
                    "count": 169628730,
                    "timestamp": 1759237324413
                },
                {
                    "count": 169961178,
                    "timestamp": 1759323946489
                },
                {
                    "count": 172171622,
                    "timestamp": 1760101506017
                },
                {
                    "count": 172243660,
                    "timestamp": 1760136586629
                },
                {
                    "count": 172695887,
                    "timestamp": 1760313438454
                },
                {
                    "count": 173133749,
                    "timestamp": 1760445323461
                },
                {
                    "count": 173489926,
                    "timestamp": 1760533473585
                },
                {
                    "count": 174490872,
                    "timestamp": 1760808887857
                },
                {
                    "count": 176482058,
                    "timestamp": 1761050957069
                },
                {
                    "count": 180700093,
                    "timestamp": 1761256679563
                },
                {
                    "count": 185074384,
                    "timestamp": 1761522907796
                },
                {
                    "count": 202311030,
                    "timestamp": 1762208008116
                },
                {
                    "count": 204571550,
                    "timestamp": 1762321931708
                }
            ]
        }
    ]
}